{
	"name": "Default Avatar",
	"parts": [
		{
			"name": "Head",
			"part": "head",
			"templateName": "Default Head",
			"position": [0, 0.6, 0]
		},
		{
			"name": "Hat",
			"part": "hat",
			"parent": "head",
			"templateName": "Default Hat",
			"position": [0, 0.42, 0.03]
		},
		{
			"name": "Torso",
			"part": "torso",
			"templateName": "Default Torso",
			"position": [0, 0, 0]
		},
		{
			"name": "Left Hand",
			"part": "left_hand",
			"templateName": "Default Left Hand",
			"position": [-0.5, -0.5, -0.1]
		},
		{
			"name": "Right Hand",
			"part": "right_hand",
			"templateName": "Default Right Hand",
			"position": [0.5, -0.5, -0.1]
		}
	]
}